ioliu/__init__.py
ioliu/app.py
ioliu/core.py
ioliu/picoperation.py
bingwp-0.1.7.dist-info/LICENSE
bingwp-0.1.7.dist-info/METADATA
bingwp-0.1.7.dist-info/WHEEL
bingwp-0.1.7.dist-info/entry_points.txt
bingwp-0.1.7.dist-info/top_level.txt
bingwp-0.1.7.dist-info/RECORD
