Metadata-Version: 2.1
Name: bingwp
Version: 0.1.7
Summary: download bing.ioliu.cn wallpaper
Home-page: https://github.com/Greatwallcorner/BingWallpaperDownload-ioliu/
Author: heatdesert
Author-email: wall.corner@outlook.com
License: MIT
Keywords: bing wallpaper download
Platform: any
Requires-Dist: bs4
Requires-Dist: tqdm
